setup.cfg
setup.py
drae/__init__.py
drae/drae.py
drae.egg-info/PKG-INFO
drae.egg-info/SOURCES.txt
drae.egg-info/dependency_links.txt
drae.egg-info/requires.txt
drae.egg-info/top_level.txt