Metadata-Version: 1.1
Name: drae
Version: 0.1.3
Summary: Query the DRAE
Home-page: https://git.hso.rocks/hso/drae
Author: José Sazo
Author-email: jose.sazo@gmail.com
License: UNKNOWN
Download-URL: https://git.hso.rocks/hso/drae/archive/0.1.3.tar.gz
Keywords: text,dictionary,api,scraping
Platform: UNKNOWN
Classifier: Development Status :: 3 - Alpha
Classifier: Programming Language :: Python :: 2
Classifier: Programming Language :: Python :: 2.7
Classifier: Programming Language :: Python :: 3
Classifier: Programming Language :: Python :: 3.4
